{
  "type": "Feature",
  "properties": {
    "name": "Blois"
  },
  "geometry": {
    "type": "Polygon",
    "coordinates": [
      [
        [
          1.2139892578125,
          47.51117174476537
        ],
        [
          1.4453887939453125,
          47.51117174476537
        ],
        [
          1.4453887939453125,
          47.62143823415564
        ],
        [
          1.2139892578125,
          47.62143823415564
        ],
        [
          1.2139892578125,
          47.51117174476537
        ]
      ]
    ]
  }
}